maufbapi/__init__.py
maufbapi/state.py
maufbapi/http/__init__.py
maufbapi/http/api.py
maufbapi/http/base.py
maufbapi/http/errors.py
maufbapi/http/login.py
maufbapi/http/post_login.py
maufbapi/http/upload.py
maufbapi/http/zstd-dict.dat
maufbapi/mqtt/__init__.py
maufbapi/mqtt/conn.py
maufbapi/mqtt/events.py
maufbapi/mqtt/otclient.py
maufbapi/mqtt/subscription.py
maufbapi/mqtt/topics.json
maufbapi/thrift/__init__.py
maufbapi/thrift/autospec.py
maufbapi/thrift/read.py
maufbapi/thrift/type.py
maufbapi/thrift/write.py
maufbapi/types/__init__.py
maufbapi/types/common.py
maufbapi/types/login.py
maufbapi/types/media.py
maufbapi/types/graphql/__init__.py
maufbapi/types/graphql/queries.py
maufbapi/types/graphql/responses.py
maufbapi/types/mqtt/__init__.py
maufbapi/types/mqtt/client_info.py
maufbapi/types/mqtt/message.py
maufbapi/types/mqtt/requests.py
mautrix_facebook/__init__.py
mautrix_facebook/__main__.py
mautrix_facebook/config.py
mautrix_facebook/example-config.yaml
mautrix_facebook/get_version.py
mautrix_facebook/matrix.py
mautrix_facebook/portal.py
mautrix_facebook/presence.py
mautrix_facebook/puppet.py
mautrix_facebook/segment_analytics.py
mautrix_facebook/user.py
mautrix_facebook/version.py
mautrix_facebook/commands/__init__.py
mautrix_facebook/commands/auth.py
mautrix_facebook/commands/conn.py
mautrix_facebook/commands/facebook.py
mautrix_facebook/commands/typehint.py
mautrix_facebook/db/__init__.py
mautrix_facebook/db/backfill_queue.py
mautrix_facebook/db/message.py
mautrix_facebook/db/portal.py
mautrix_facebook/db/puppet.py
mautrix_facebook/db/reaction.py
mautrix_facebook/db/user.py
mautrix_facebook/db/user_portal.py
mautrix_facebook/db/upgrade/__init__.py
mautrix_facebook/db/upgrade/v01_initial_revision.py
mautrix_facebook/db/upgrade/v02_message_oti.py
mautrix_facebook/db/upgrade/v03_portal_meta_set.py
mautrix_facebook/db/upgrade/v04_relay_mode.py
mautrix_facebook/db/upgrade/v05_remove_communities.py
mautrix_facebook/db/upgrade/v06_store_user_seq_id.py
mautrix_facebook-0.5.1.dist-info/LICENSE
mautrix_facebook-0.5.1.dist-info/METADATA
mautrix_facebook-0.5.1.dist-info/WHEEL
mautrix_facebook-0.5.1.dist-info/top_level.txt
mautrix_facebook-0.5.1.dist-info/RECORD
